predictit_markets/__init__.py
predictit_markets/predictit_markets.py
tests/__init__.py
tests/test_integration_predictit_markets.py
tests/test_predictit_markets.py
predictit_markets-0.1.5.dist-info/METADATA
predictit_markets-0.1.5.dist-info/WHEEL
predictit_markets-0.1.5.dist-info/top_level.txt
predictit_markets-0.1.5.dist-info/RECORD
