Metadata-Version: 2.1
Name: predictit-markets
Version: 0.1.5
Summary: A package for interacting with PredictIt markets
Home-page: https://github.com/tuttlepower/predictit_markets
Author: Travis Tuttle
Author-email: 28586132+tuttlepower@users.noreply.github.com
Classifier: Programming Language :: Python :: 3
Classifier: License :: OSI Approved :: MIT License
Classifier: Operating System :: OS Independent
Requires-Python: >=3.6
Requires-Dist: requests
Requires-Dist: pandas
